.cruft.json
.gitignore
.pre-commit-config.yaml
CHANGES.rst
CITATION.cff
CODE_OF_CONDUCT.md
CONTRIBUTING.md
LICENSE
MANIFEST.in
README.rst
codespell-ignore.txt
pyproject.toml
setup.py
tox.ini
.github/CODEOWNERS
.github/dependabot.yml
.github/labeler.yml
.github/ISSUE_TEMPLATE/FEATURE_REQUEST.md
.github/ISSUE_TEMPLATE/ISSUE_TEMPLATE.md
.github/ISSUE_TEMPLATE/PR_TEMPLATE.md
.github/workflows/changelog.yml
.github/workflows/run_labeler.yml
.github/workflows/run_snpit_utils_tests.yml
.github/workflows/sphinx-deploy.yml
.github/workflows/sub_package_update.yml
changes/.gitkeep
changes/1.feature.rst
changes/11.feature.rst
changes/12.docs.rst
changes/13.bugfix.rst
changes/14.feature.rst
changes/15.feature.rst
changes/16.feature.rst
changes/17.snpit_utils.rst
changes/2.bugfix.rst
changes/3.snpit_utils.rst
changes/4.docs.rst
changes/5.docs.rst
changes/6.docs.rst
changes/8.feature.rst
docs/Makefile
docs/api.rst
docs/changes.rst
docs/conf.py
docs/index.rst
docs/installation.rst
docs/make.bat
docs/usage.rst
docs/_static/logo_black_filled.png
snpit_utils/__init__.py
snpit_utils/_version.py
snpit_utils/config.py
snpit_utils/db_backup.py
snpit_utils/http.py
snpit_utils/logger.py
snpit_utils/utils.py
snpit_utils.egg-info/PKG-INFO
snpit_utils.egg-info/SOURCES.txt
snpit_utils.egg-info/dependency_links.txt
snpit_utils.egg-info/not-zip-safe
snpit_utils.egg-info/requires.txt
snpit_utils.egg-info/top_level.txt
snpit_utils/data/README.rst