Metadata-Version: 2.4
Name: snpit_utils
Version: 0.2.0
Summary: Base utilities for the Roman SNPIT
Author: Roman Supernova Project Infrastructure Team
Maintainer-email: "Rob Knop et al." <raknop@lbl.gov>
Project-URL: repository, https://github.com/Roman-Supernova-PIT
Classifier: Development Status :: 3 - Alpha
Classifier: Programming Language :: Python
Requires-Python: >=3.11
License-File: LICENSE
Requires-Dist: numpy<3.0.0,>=2.2.6
Requires-Dist: pyyaml<7.0.0,>=6.0.3
Requires-Dist: requests<3.0.0,>=2.32.5
Requires-Dist: rkwebutil<3.0.0,>=2.1.1
Requires-Dist: simplejson<4.0.0,>=3.20.2
Provides-Extra: test
Requires-Dist: pytest; extra == "test"
Requires-Dist: pytest-doctestplus; extra == "test"
Requires-Dist: pytest-cov; extra == "test"
Requires-Dist: requests; extra == "test"
Requires-Dist: tox; extra == "test"
Requires-Dist: devpi_process; extra == "test"
Provides-Extra: docs
Requires-Dist: sphinx; extra == "docs"
Requires-Dist: sphinx-automodapi; extra == "docs"
Requires-Dist: matplotlib; extra == "docs"
Requires-Dist: sphinx; extra == "docs"
Requires-Dist: tomli; extra == "docs"
Requires-Dist: graphviz; extra == "docs"
Dynamic: license-file
